beets_follow-1.1.0.dist-info/DESCRIPTION.rst
beets_follow-1.1.0.dist-info/METADATA
beets_follow-1.1.0.dist-info/RECORD
beets_follow-1.1.0.dist-info/WHEEL
beets_follow-1.1.0.dist-info/metadata.json
beets_follow-1.1.0.dist-info/top_level.txt
beetsplug/__init__.py
beetsplug/follow.py
