Metadata-Version: 2.0
Name: beets-follow
Version: 1.1.0
Summary: Plugin for the music library manager Beets. Follow artists from your library using muspy.com
Home-page: https://github.com/nolsto/beets-follow
Author: Nolan Stover
Author-email: nolan@nolsto.com
License: MIT
Download-URL: https://github.com/nolsto/beets-follow.git
Keywords: beets muspy
Platform: UNKNOWN
Classifier: License :: OSI Approved :: MIT License
Classifier: Programming Language :: Python :: 2
Classifier: Programming Language :: Python :: 2.7
Classifier: Programming Language :: Python :: 3
Classifier: Programming Language :: Python :: 3.4
Classifier: Programming Language :: Python :: 3.5
Classifier: Programming Language :: Python :: 3.6
Requires-Dist: beets (>=1.4.3)
